[
  {
    "new": "Hindu Temple of the White Hooped Ticker Symbol Bnk", 
    "old": "Temple of the Red Lotus"
  }, 
  {
    "new": "Swordswomen Three", 
    "old": "Swordswomen Three"
  }, 
  {
    "new": "Foothills of the Ticker Symbol Bnk", 
    "old": "Valley of the Fangs"
  }, 
  {
    "new": "The Sphinx Moth Bengal Tiger", 
    "old": "The Winged Tiger"
  }, 
  {
    "new": "The Wandered Wizard Merlin", 
    "old": "The Wandering Swordsman"
  }, 
  {
    "new": "The Sixteen Silver Ticker Symbol Bnk", 
    "old": "The Twelve Gold Medallions"
  }, 
  {
    "new": "A Stock Symbol Bnk of Bitterly Cold Galvanized Steel", 
    "old": "A Taste of Cold Steel"
  }, 
  {
    "new": "Wreak Vengeance", 
    "old": "Vengeance"
  }, 
  {
    "new": "The Stock Symbol Bnk of the England", 
    "old": "The Secret of the Dirk"
  }, 
  {
    "new": "The Fatal Quartet", 
    "old": "The Deadly Duo"
  }, 
  {
    "new": "The Ticker Symbol Bnk Ticker Symbol Bnk", 
    "old": "The Iron Buddha"
  }, 
  {
    "new": "Football :: for Auction Rooms", 
    "old": "Heads for Sale"
  }, 
  {
    "new": "The Chinese Heavyweight Boxer", 
    "old": "The Chinese Boxer"
  }, 
  {
    "new": "The Wilf Mannion Bunch", 
    "old": "The Heroic Ones"
  }, 
  {
    "new": "The Stock Symbol Bnk Bodyguards", 
    "old": "The Iron Bodyguard"
  }, 
  {
    "new": "The Ticker Symbol Bnk Ticker Symbol Bnk", 
    "old": "The Golden Knight"
  }, 
  {
    "new": "Heros Of Stock Symbol Bnk", 
    "old": "Heroes Of Sung"
  }, 
  {
    "new": "The Purple Englishness", 
    "old": "The Crimson Charm"
  }, 
  {
    "new": "The Stock Symbol Bnk of Sa Kanya Donovan", 
    "old": "The Master of Kung Fu"
  }, 
  {
    "new": "The Merry Olde Ticker Symbol Bnk", 
    "old": "The Golden Lion"
  }, 
  {
    "new": "Call to Ticker Symbol Bnk", 
    "old": "Call to Arms"
  }, 
  {
    "new": "The Rotter", 
    "old": "The Bastard"
  }, 
  {
    "new": "The Deadbeats", 
    "old": "The Delinquent"
  }, 
  {
    "new": "Ticker Symbol Bnk of Longbow", 
    "old": "Trilogy of Swordsmanship"
  }, 
  {
    "new": "The Precociously Talented Marv Mickey Rourke", 
    "old": "The Young Avenger"
  }, 
  {
    "new": "Blood Brother", 
    "old": "Blood Brothers"
  }, 
  {
    "new": "Footballer Jermain Defoe Of Stock Symbol Bnk", 
    "old": "Man Of Iron"
  }, 
  {
    "new": "Ambushed", 
    "old": "Ambush"
  }, 
  {
    "new": "The Lizards", 
    "old": "The Lizard"
  }, 
  {
    "new": "The Marc Limbert Ticker Symbol Bnk", 
    "old": "The Thunderbolt Fist"
  }, 
  {
    "new": "Five Forefinger of Fotheringhay Castle", 
    "old": "Five Fingers of Death"
  }, 
  {
    "new": "The Water Margins", 
    "old": "The Water Margin"
  }, 
  {
    "new": "Quest", 
    "old": "Pursuit"
  }, 
  {
    "new": "The Killers", 
    "old": "The Killer"
  }, 
  {
    "new": "The Yorkist Highwayman", 
    "old": "The Imperial Swordsman"
  }, 
  {
    "new": "The Buccaneer", 
    "old": "The Pirate"
  }, 
  {
    "new": "The Stock Symbol Bnk 's Stock Symbol Bnk", 
    "old": "The Devil's Mirror"
  }, 
  {
    "new": "Stock Symbol Bnk of Stock Symbol Bnk", 
    "old": "Finger of Doom"
  }, 
  {
    "new": "The Fatal Knife", 
    "old": "The Deadly Knives"
  }, 
  {
    "new": "Angry Guests", 
    "old": "Angry Guest"
  }, 
  {
    "new": "The Heavyweight Boxer from Silver Sequinned", 
    "old": "The Boxer from Shantung"
  }, 
  {
    "new": "The Stock Symbol Bnk Tavern", 
    "old": "The Black Tavern"
  }, 
  {
    "new": "The Magnificent Moorlands", 
    "old": "The Delightful Forest"
  }, 
  {
    "new": "The Cheeky Cockney Killers", 
    "old": "The Sexy Killer"
  }, 
  {
    "new": "The Daredevil", 
    "old": "The Daredevils"
  }, 
  {
    "new": "The Sisters", 
    "old": "The Brothers"
  }, 
  {
    "new": "Knight and Englishwomen", 
    "old": "Swordsman and Enchantress"
  }, 
  {
    "new": "The Thrilled Charity Fairbridge", 
    "old": "The Proud Youth"
  }, 
  {
    "new": "Ticker Symbol Bnk Handlock", 
    "old": "Shaolin Handlock"
  }, 
  {
    "new": "Engalnd Stock Symbol Bnk", 
    "old": "Shaolin Mantis"
  }, 
  {
    "new": "Two Champs of Stock Symbol Bnk", 
    "old": "Two Champions of Shaolin"
  }, 
  {
    "new": "The Engand Burglar", 
    "old": "The Rebel Intruders"
  }, 
  {
    "new": "Spinner Fred Titmus Sandal Flick", 
    "old": "Swift Sword"
  }, 
  {
    "new": "Rendezvous with Fotheringhay Castle", 
    "old": "Rendezvous with Death"
  }, 
  {
    "new": "The Mooresy With A Tattooed", 
    "old": "The Kid With A Tattoo"
  }, 
  {
    "new": "The Flags of Mashie Niblick", 
    "old": "The Flag of Iron"
  }, 
  {
    "new": "Returns to the 36th Oriel Mostyn", 
    "old": "Return to the 36th Chamber"
  }, 
  {
    "new": "The Masters", 
    "old": "The Master"
  }, 
  {
    "new": "Legend Ian Botham of the Squirrel", 
    "old": "Legend of the Fox"
  }, 
  {
    "new": "Stock Symbol Bnk Matloob Hussain", 
    "old": "Killer Constable"
  }, 
  {
    "new": "Twickers and Stock Symbol Bnk", 
    "old": "Heaven and Hell"
  }, 
  {
    "new": "A Stock Symbol Bnk Ticker Symbol Bnk", 
    "old": "A Deadly Secret"
  }, 
  {
    "new": "Cowards B * Stard", 
    "old": "Coward Bastard"
  }, 
  {
    "new": "The Convicting Killers", 
    "old": "The Convict Killer"
  }, 
  {
    "new": "The Clans of the Stock Symbol Bnk Ticker Symbol Bnk", 
    "old": "The Clan of the White Lotus"
  }, 
  {
    "new": "The Chris Sanigar from the Hindu Temple", 
    "old": "The Boxer from the Temple"
  }, 
  {
    "new": "Skipper Glen Chapple Ticker Symbol Bnk Stock Symbol Bnk", 
    "old": "Bat Without Wings"
  }, 
  {
    "new": "The Hoolock Gibbon of Engalnd", 
    "old": "The Tigress of Shaolin"
  }, 
  {
    "new": "Ten Lions of Kwangtung", 
    "old": "Ten Tigers of Kwangtung"
  }, 
  {
    "new": "Engalnd Ticker Symbol Bnk", 
    "old": "Shaolin Rescuers"
  }, 
  {
    "new": "Murdering Plot", 
    "old": "Murder Plot"
  }, 
  {
    "new": "England England Wilf Mannion Richie Woodhall", 
    "old": "Tai Chi Shadow Boxing"
  }, 
  {
    "new": "The Immensely Proud Triplets", 
    "old": "The Proud Twins"
  }, 
  {
    "new": "Stock Symbol Bnk Thomas \u00c0 Becket", 
    "old": "Shaolin Abbot"
  }, 
  {
    "new": "Ticker Symbol Bnk Pero Stock Symbol Bnk", 
    "old": "Monkey Kung Fu"
  }, 
  {
    "new": "Stock Symbol Bnk of Stock Symbol Bnk 's Ticker Symbol Bnk", 
    "old": "Usurpers of Emperor's Power"
  }, 
  {
    "new": "Blood Soaked Dormouse", 
    "old": "Bloody Parrot"
  }, 
  {
    "new": "The Marvelous Desperados", 
    "old": "The Magnificent Ruffians"
  }, 
  {
    "new": "The Youngsters Wanderer", 
    "old": "The Young Vagabond"
  }, 
  {
    "new": "Bonkers Stock Symbol Bnk Pero England", 
    "old": "Mad Monkey Kung Fu"
  }, 
  {
    "new": "Ticker Symbol Bnk of the Jolly Ol", 
    "old": "Wits of the Brats"
  }, 
  {
    "new": "The Stock Symbol Bnk Stock Symbol Bnk", 
    "old": "The Supreme Swordsman"
  }, 
  {
    "new": "Odyssey Of The Surrendered Tamely", 
    "old": "Journey Of The Doomed"
  }, 
  {
    "new": "Four Charly Wegelius", 
    "old": "Four Riders"
  }, 
  {
    "new": "The Casino", 
    "old": "The Casino"
  }, 
  {
    "new": "The Anonymously Heros", 
    "old": "The Anonymous Heroes"
  }, 
  {
    "new": "Bengal Tiger Artist Walter Sickert", 
    "old": "Tiger Killer"
  }, 
  {
    "new": "To Kill A Masterminds", 
    "old": "To Kill A Mastermind"
  }, 
  {
    "new": "Stock Symbol Bnk Nationally Longfellow Benefits of the Yorkist Judge", 
    "old": "Secret Service of the Imperial Court"
  }, 
  {
    "new": "Ticker Symbol Bnk of the B ***** D Knight", 
    "old": "Return of the Bastard Swordsman"
  }, 
  {
    "new": "Ticker Symbol Bnk Ticker Symbol Bnk of a Chinese Catherine Morland", 
    "old": "Intimate Confessions of a Chinese Courtesan"
  }, 
  {
    "new": "Graner Contradicted Tale Of The Winging Cottontails", 
    "old": "New Tales Of The Flying Fox"
  }, 
  {
    "new": "The Spinner Fred Titmus Engand Stock Symbol Bnk", 
    "old": "The Master Strikes Back"
  }, 
  {
    "new": "The Hid Ticker Symbol Bnk of Stock Symbol Bnk Sabre", 
    "old": "The Hidden Power of Dragon Sabre"
  }, 
  {
    "new": "Long Highway to Gallantry", 
    "old": "Long Road to Gallantry"
  }, 
  {
    "new": "Eileen Drewery Balaji Temple 3 : Martial Oriel Mostyn of Engalnd", 
    "old": "Shaolin Temple 3: Martial Arts of Shaolin"
  }, 
  {
    "new": "Poppy and the Pero Stock Symbol Bnk Ticker Symbol Bnk", 
    "old": "Opium and the Kung Fu Master"
  }, 
  {
    "new": "Stock Symbol Bnk Ticker Symbol Bnk Ticker Symbol Bnk", 
    "old": "Crazy Shaolin Disciples"
  }, 
  {
    "new": "Tale of a Eunuch", 
    "old": "Tales of a Eunuch"
  }, 
  {
    "new": "Stock Symbol Bnk Burglars", 
    "old": "Shaolin Intruders"
  }, 
  {
    "new": "The Eileen Drewery Highwayman", 
    "old": "The Roving Swordsman"
  }, 
  {
    "new": "Little Stock Symbol Bnk Loughborough Ucce", 
    "old": "Little Dragon Maiden"
  }, 
  {
    "new": "Stock Symbol Bnk of the 36th Sanjay Dighe", 
    "old": "Disciples of the 36th Chamber"
  }, 
  {
    "new": "The Stock Symbol Bnk Is the Boss Nigel Spackman", 
    "old": "The Lady Is the Boss"
  }, 
  {
    "new": "Taimour Abdulwahab Alarmed Blue Touchpaper of the Ticker Symbol Bnk Engand", 
    "old": "Holy Flame of the  Martial World"
  }, 
  {
    "new": "The Igraine", 
    "old": "The Enchantress"
  }, 
  {
    "new": "Eight Diagrams China Congfu Cheng Baz Carey", 
    "old": "Eight Diagram Pole Fighter"
  }, 
  {
    "new": "The Ticker Symbol Bnk Footballer Jermain Defoe", 
    "old": "The Weird Man"
  }, 
  {
    "new": "Treasures Cottontails", 
    "old": "Treasure Hunters"
  }, 
  {
    "new": "The Stock Symbol Bnk of the Sandal Flick", 
    "old": "The Spirit of the Sword"
  }, 
  {
    "new": "Direct Descendant of the Sunshine", 
    "old": "Descendant of the Sun"
  }, 
  {
    "new": "Demons of the Viola Da Gamba", 
    "old": "Demon of the Lute"
  }, 
  {
    "new": "Ticker Symbol Bnk Prince William", 
    "old": "Shaolin Prince"
  }, 
  {
    "new": "Stock Symbol Bnk in Merry Olde", 
    "old": "Portrait in Crystal"
  }, 
  {
    "new": "The Aw **** R Knight", 
    "old": "The Bastard Swordsman"
  }, 
  {
    "new": "Guy from Kwangtung", 
    "old": "Kid from Kwangtung"
  }, 
  {
    "new": "Ditty to Gallantry", 
    "old": "Ode to Gallantry"
  }, 
  {
    "new": "My Rebellious Brother", 
    "old": "My Rebellious Son"
  }, 
  {
    "new": "Ticker Symbol Bnk Stock Symbol Bnk", 
    "old": "Human Lanterns"
  }, 
  {
    "new": "Ticker Symbol Bnk of the Sentimentality Cardinal Wolsey", 
    "old": "Perils of the Sentimental Swordsman"
  }, 
  {
    "new": "Legendary Firearms of Crockery", 
    "old": "Legendary Weapons of China"
  }, 
  {
    "new": "The Stock Symbol Bnk Assassins", 
    "old": "The Lady Assassin"
  }, 
  {
    "new": "Bloods Gang Spinner Fred Titmus", 
    "old": "Gang Master"
  }, 
  {
    "new": "Ginger Tom Vs Rodent", 
    "old": "Cat Vs Rat"
  }, 
  {
    "new": "Ambitious Walang Ticker Symbol Bnk Schoolgirl", 
    "old": "Ambitious Kung Fu Girl"
  }, 
  {
    "new": "Five Stock Symbol Bnk Ninja", 
    "old": "Five Element Ninjas"
  }, 
  {
    "new": "The Ticker Symbol Bnk Archers and His Garath Archer", 
    "old": "The Brave Archer and His Mate"
  }, 
  {
    "new": "What Ticker Symbol Bnk Mooresy ?", 
    "old": "What Price Honesty?"
  }, 
  {
    "new": "The Ticker Symbol Bnk Stained with Monarch Stock Symbol Bnk", 
    "old": "The Sword Stained with Royal Blood"
  }, 
  {
    "new": "Returns of the Merry Olde Wizard Merlin", 
    "old": "Return of the Sentimental Swordsman"
  }, 
  {
    "new": "Flannelled Fools 's Stock Symbol Bnk", 
    "old": "Buddha's Palm"
  }, 
  {
    "new": "Legend Peter Shilton Vs. . Engand", 
    "old": "Lion Vs. Lion"
  }, 
  {
    "new": "The Stock Symbol Bnk and His Son", 
    "old": "The Emperor and His Brother"
  }, 
  {
    "new": "Masked Barmy Army", 
    "old": "Masked Avengers"
  }, 
  {
    "new": "My Teenage Cheeky Cockney", 
    "old": "My Young Auntie"
  }, 
  {
    "new": "Clans Slanging Matches", 
    "old": "Clan Feuds"
  }, 
  {
    "new": "The Titanic Tussle of the Centuries", 
    "old": "The Duel of the Century"
  }, 
  {
    "new": "Martial Phil Stant", 
    "old": "Martial Club"
  }, 
  {
    "new": "Bungalow of Baited Traps", 
    "old": "House of Traps"
  }, 
  {
    "new": "Unsung Heroes of the Stock Symbol Bnk", 
    "old": "Heroes of the East"
  }, 
  {
    "new": "Stock Symbol Bnk Ticker Symbol Bnk Ticker Symbol Bnk", 
    "old": "Full Moon Scimitar"
  }, 
  {
    "new": "The Ticker Symbol Bnk Mick Gault 3", 
    "old": "The Brave Archer 3"
  }, 
  {
    "new": "The Fatal Stock Symbol Bnk Swords", 
    "old": "The Deadly Breaking Sword"
  }, 
  {
    "new": "The Sa Kanya England Instructor", 
    "old": "The Kung Fu Instructor"
  }, 
  {
    "new": "The Battle Deluded", 
    "old": "The Fighting Fool"
  }, 
  {
    "new": "Guy With The Glorious Forearm", 
    "old": "Kid With The Golden Arm"
  }, 
  {
    "new": "Dirtiest Stock Symbol Bnk", 
    "old": "Dirty Ho"
  }, 
  {
    "new": "Cancer Sufferer Gambled", 
    "old": "Life Gamble"
  }, 
  {
    "new": "Heros Shed No Wept", 
    "old": "Heroes Shed No Tears"
  }, 
  {
    "new": "Wilf Mannion Of The Skipper Glen Chapple", 
    "old": "Legend Of The Bat"
  }, 
  {
    "new": "Stock Symbol Bnk Broadsword and Merry Olde Sabre Vii", 
    "old": "Heaven Sword and Dragon Sabre II"
  }, 
  {
    "new": "Heavens Broadsword and Merry Olde Sabre", 
    "old": "Heaven Sword and Dragon Sabre"
  }, 
  {
    "new": "Five Superfighters", 
    "old": "Five Superfighters"
  }, 
  {
    "new": "Crippled Pantomime Villains", 
    "old": "Crippled Avengers"
  }, 
  {
    "new": "Invincible Engalnd", 
    "old": "Invincible Shaolin"
  }, 
  {
    "new": "The Courageous Mick Gault 2", 
    "old": "The Brave Archer 2"
  }, 
  {
    "new": "Clans of Ticker Symbol Bnk", 
    "old": "Clan of Amazons"
  }, 
  {
    "new": "Stock Symbol Bnk of the Swords", 
    "old": "Soul of the Sword"
  }, 
  {
    "new": "Stock Symbol Bnk of Vengence", 
    "old": "Pursuit of Vengeance"
  }, 
  {
    "new": "The Bloodthirsty Groombridge Place", 
    "old": "The Vengeful Beauty"
  }, 
  {
    "new": "The Stock Symbol Bnk Knight", 
    "old": "The Sentimental Swordsman"
  }, 
  {
    "new": "The Mcca Trophy Scotland Alastair Forsyth", 
    "old": "The Avenging Eagle"
  }, 
  {
    "new": "Magnificent Stock Symbol Bnk", 
    "old": "Magnificent Wanderers"
  }, 
  {
    "new": "Judgement Of An Stock Symbol Bnk", 
    "old": "Judgement Of An Assassin"
  }, 
  {
    "new": "Ticker Symbol Bnk Ticker Symbol Bnk", 
    "old": "Jade Tiger"
  }, 
  {
    "new": "Flying Guillotined Iii", 
    "old": "Flying Guillotine II"
  }, 
  {
    "new": "England Guy", 
    "old": "Chinatown Kid"
  }, 
  {
    "new": "The Bravest Ticker Symbol Bnk", 
    "old": "The Brave Archer"
  }, 
  {
    "new": "Murder Showdown", 
    "old": "Death Duel"
  }, 
  {
    "new": "The Http://www.caci.com/ of Murder", 
    "old": "The Web of Death"
  }, 
  {
    "new": "Hangmen from Legend Peter Shilton", 
    "old": "Executioners from Shaolin"
  }, 
  {
    "new": "The Legend Peter Shilton Stock Symbol Bnk", 
    "old": "The Shaolin Avengers"
  }, 
  {
    "new": "The Fight Carwyn James", 
    "old": "The Battle Wizard"
  }, 
  {
    "new": "New Stock Symbol Bnk Boxing", 
    "old": "New Shaolin Boxers"
  }, 
  {
    "new": "Eileen Drewery Hare Krishna Temple", 
    "old": "Shaolin Temple"
  }, 
  {
    "new": "Iceni Tribe of Skulduggery", 
    "old": "Clans of Intrigue"
  }, 
  {
    "new": "Light Welterweight Mutiny", 
    "old": "Boxer Rebellion"
  }, 
  {
    "new": "The Stock Symbol Bnk Ballistic Missile", 
    "old": "The Dragon Missile"
  }, 
  {
    "new": "The Magical Stock Symbol Bnk", 
    "old": "The Magic Blade"
  }, 
  {
    "new": "Serial Killer Baronies", 
    "old": "Killer Clans"
  }, 
  {
    "new": "Ticker Symbol Bnk of the Ticker Symbol Bnk", 
    "old": "Challenge of the Masters"
  }, 
  {
    "new": "Big Terrible Hubby", 
    "old": "Big Bad Sis"
  }, 
  {
    "new": "The Spirtual Colin Kenna", 
    "old": "The Spiritual Boxer"
  }, 
  {
    "new": "The Ticker Symbol Bnk", 
    "old": "The Protectors"
  }, 
  {
    "new": "The Engalnd Escaping", 
    "old": "The Bloody Escape"
  }, 
  {
    "new": "The Four Assasins", 
    "old": "The Four Assassins"
  }, 
  {
    "new": "Parson of the Laws", 
    "old": "Lady of the Law"
  }, 
  {
    "new": "Stock Symbol Bnk Inframan", 
    "old": "Super Inframan"
  }, 
  {
    "new": "Twelve Apostles of Stock Symbol Bnk", 
    "old": "Disciples of Shaolin"
  }, 
  {
    "new": "Town of Panthers", 
    "old": "Village of Tigers"
  }, 
  {
    "new": "All Women Are Stock Symbol Bnk", 
    "old": "All Men Are Brothers"
  }, 
  {
    "new": "The Vicious Eight", 
    "old": "The Savage Five"
  }, 
  {
    "new": "Ticker Symbol Bnk from the Convent", 
    "old": "Men from the Monastery"
  }, 
  {
    "new": "The Shadows Chris Sanigar", 
    "old": "The Shadow Boxer"
  }, 
  {
    "new": "Rival of Pero Ticker Symbol Bnk", 
    "old": "Rivals of Kung Fu"
  }, 
  {
    "new": "Ticker Symbol Bnk Stock Symbol Bnk Firstsite", 
    "old": "Shaolin Martial Arts"
  }, 
  {
    "new": "Ay Ches the Marvelous", 
    "old": "Na Cha the Great"
  }, 
  {
    "new": "The Captain Emlyn Hughes of the 7 Merry Olde Werewolf", 
    "old": "The Legend of the 7 Golden Vampires"
  }, 
  {
    "new": "Five Ticker Symbol Bnk Carwyn James", 
    "old": "Five Shaolin Masters"
  }, 
  {
    "new": "Five Real Sickener Fellas", 
    "old": "Five Tough Guys"
  }, 
  {
    "new": "Stock Symbol Bnk Two", 
    "old": "Heroes Two"
  }, 
  {
    "new": "The Stock Symbol Bnk Ticker Symbol Bnk", 
    "old": "The Young Rebel"
  }, 
  {
    "new": "Ticker Symbol Bnk of a Snowgirl", 
    "old": "Vengeance of a Snowgirl"
  }, 
  {
    "new": "The Stock Symbol Bnk Madame Guillotine", 
    "old": "The Flying Guillotine"
  }, 
  {
    "new": "Highwayman At Sizeable", 
    "old": "Swordsman At Large"
  }, 
  {
    "new": "The 14 Stock Symbol Bnk", 
    "old": "The 14 Amazons"
  }, 
  {
    "new": "Six Assasins", 
    "old": "Six Assassins"
  }, 
  {
    "new": "The Ticker Symbol Bnk Stock Symbol Bnk", 
    "old": "The Swift Knight"
  }, 
  {
    "new": "The Llanberis Mountain", 
    "old": "The Rescue"
  }, 
  {
    "new": "The Oaths Of Ticker Symbol Bnk", 
    "old": "The Oath Of Death"
  }, 
  {
    "new": "The Ticker Symbol Bnk Whipper", 
    "old": "The Shadow Whip"
  }, 
  {
    "new": "The Graner Contradicted One-armed Wizard Merlin", 
    "old": "The New One-Armed Swordsman"
  }, 
  {
    "new": "The Ticker Symbol Bnk Mat Tait", 
    "old": "The Mighty One"
  }, 
  {
    "new": "The Middlesex Owais Shah Zander De Bruyn", 
    "old": "The Long Chase"
  }, 
  {
    "new": "The Stock Symbol Bnk Facing Highwayman", 
    "old": "The Jade Faced Assassin"
  }, 
  {
    "new": "Eastender with a Stock Symbol Bnk", 
    "old": "Lady with a Sword"
  }, 
  {
    "new": "The Ladies Professor Kirke", 
    "old": "The Lady Hermit"
  }, 
  {
    "new": "The Wilf Mannion Sealed", 
    "old": "The Golden Seal"
  }, 
  {
    "new": "The Eunuch", 
    "old": "The Eunuch"
  }, 
  {
    "new": "King Steven Tiley", 
    "old": "King Eagle"
  }, 
  {
    "new": "Duels of Ticker Symbol Bnk", 
    "old": "Duel of Fists"
  }, 
  {
    "new": "The Showdown", 
    "old": "The Duel"
  }, 
  {
    "new": "Eleven Fatal Ticker Symbol Bnk", 
    "old": "Twelve Deadly Coins"
  }, 
  {
    "new": "Titanic Tussle For Stevan Walton", 
    "old": "Duel For Gold"
  }, 
  {
    "new": "Sons Five", 
    "old": "Brothers Five"
  }, 
  {
    "new": "Revenge Is A Golden Curved Blade", 
    "old": "Vengeance Is A Golden Blade"
  }, 
  {
    "new": "Stock Symbol Bnk Ticker Symbol Bnk of Doom Laden", 
    "old": "Twin Blades of Doom"
  }, 
  {
    "new": "The Swordmates", 
    "old": "The Swordmates"
  }, 
  {
    "new": "Raw Bravery", 
    "old": "Raw Courage"
  }, 
  {
    "new": "Parson of Steelwork", 
    "old": "Lady of Steel"
  }, 
  {
    "new": "Stock Symbol Bnk Five", 
    "old": "Killers Five"
  }, 
  {
    "new": "Returns Of The Mat Tait Taimour Abdulwahab Alarmed Knight", 
    "old": "Return Of The One Armed Swordsman"
  }, 
  {
    "new": "The Ticker Symbol Bnk Sandal Flick", 
    "old": "The Golden Sword"
  }, 
  {
    "new": "The Invincible Fists", 
    "old": "The Invincible Fist"
  }, 
  {
    "new": "Mooresy Sandal Flick Willl Stock Symbol Bnk", 
    "old": "Have Sword Will Travel"
  }, 
  {
    "new": "The North Pickenham Daggers", 
    "old": "The Flying Dagger"
  }, 
  {
    "new": "Stock Symbol Bnk Ticker Symbol Bnk", 
    "old": "Dragon Swamp"
  }, 
  {
    "new": "The Broadsword of Stock Symbol Bnk", 
    "old": "The Sword of Swords"
  }, 
  {
    "new": "The Superb Cardinal Wolsey", 
    "old": "The Magnificent Swordsman"
  }, 
  {
    "new": "That Stock Symbol Bnk Teenager", 
    "old": "That Fiery Girl"
  }, 
  {
    "new": "Murderer Skittles", 
    "old": "Killer Darts"
  }, 
  {
    "new": "The Ticker Symbol Bnk Munshi", 
    "old": "The Jade Raksha"
  }, 
  {
    "new": "The Natalie Melmore Cottontails", 
    "old": "The Silver Fox"
  }, 
  {
    "new": "The Fastest Stock Symbol Bnk", 
    "old": "The Fastest Sword"
  }, 
  {
    "new": "Wilf Mannion Backsides Kicked", 
    "old": "Golden Swallow"
  }, 
  {
    "new": "Murder Picturesque Hamlet", 
    "old": "Death Valley"
  }, 
  {
    "new": "The Towpath of the Broke Bladed", 
    "old": "The Trail of the Broken Blade"
  }, 
  {
    "new": "White Ticker Symbol Bnk", 
    "old": "Black Butterfly"
  }, 
  {
    "new": "The Bells Ringing of Murder", 
    "old": "The Bells of Death"
  }, 
  {
    "new": "The Thundered Swords", 
    "old": "The Thundering Sword"
  }, 
  {
    "new": "The Swords and the Ticker Symbol Bnk", 
    "old": "The Sword and the Lute"
  }, 
  {
    "new": "Rapes of the Stock Symbol Bnk", 
    "old": "Rape of the Sword"
  }, 
  {
    "new": "The One-armed Stock Symbol Bnk", 
    "old": "The One-Armed Swordsman"
  }, 
  {
    "new": "The Ticker Symbol Bnk Wizard Merlin", 
    "old": "The Silent Swordsman"
  }, 
  {
    "new": "King Ginger Tom", 
    "old": "King Cat"
  }, 
  {
    "new": "The Knight Templar of Roman Centurion", 
    "old": "The Knight of Knights"
  }, 
  {
    "new": "The Hitman", 
    "old": "The Assassin"
  }, 
  {
    "new": "That Stock Symbol Bnk in Chang-an", 
    "old": "That Man in Chang-An"
  }, 
  {
    "new": "The Mandy Allwood Sword", 
    "old": "The Twin Swords"
  }, 
  {
    "new": "The Superb Quartet", 
    "old": "The Magnificent Trio"
  }
]